{"stats":{"minecraft:custom":{"minecraft:animals_bred":3,"minecraft:interact_with_crafting_table":168,"minecraft:open_barrel":47,"minecraft:bell_ring":4,"minecraft:leave_game":52,"minecraft:time_since_death":35361,"minecraft:damage_resisted":10,"minecraft:sprint_one_cm":1977152,"minecraft:damage_blocked_by_shield":942,"minecraft:drop":217,"minecraft:talked_to_villager":3,"minecraft:play_time":1149684,"minecraft:deaths":55,"minecraft:jump":10367,"minecraft:walk_on_water_one_cm":144061,"minecraft:interact_with_furnace":81,"minecraft:interact_with_loom":1,"minecraft:sleep_in_bed":28,"minecraft:damage_dealt":12082,"minecraft:player_kills":20,"minecraft:crouch_one_cm":54047,"minecraft:interact_with_smoker":24,"minecraft:horse_one_cm":30,"minecraft:interact_with_smithing_table":1,"minecraft:mob_kills":83,"minecraft:inspect_hopper":3,"minecraft:interact_with_campfire":1,"minecraft:damage_dealt_resisted":48,"minecraft:climb_one_cm":67989,"minecraft:walk_one_cm":3036458,"minecraft:sneak_time":22502,"minecraft:walk_under_water_one_cm":106853,"minecraft:boat_one_cm":3518375,"minecraft:interact_with_blast_furnace":40,"minecraft:total_world_time":1149684,"minecraft:pot_flower":2,"minecraft:interact_with_stonecutter":1,"minecraft:time_since_rest":35365,"minecraft:damage_taken":20317,"minecraft:trigger_trapped_chest":33,"minecraft:swim_one_cm":80184,"minecraft:fly_one_cm":1491650,"minecraft:open_chest":875,"minecraft:fall_one_cm":269940},"minecraft:used":{"minecraft:moss_block":2,"meadow:fire_lily":3,"minecraft:iron_shovel":289,"refurbished_furniture:spruce_drawer":4,"create:scorchia":1,"meadow:table":6,"minecraft:spruce_slab":2,"farmersdelight:cabbage_seeds":16,"minecraft:poppy":1,"minecraft:shield":19,"minecraft:stone":6,"minecraft:rotten_flesh":7,"tacz-fabric:gun_smith_table":1,"create:mechanical_bearing":3,"supplementaries:globe":3,"meadow:stove_tiles":5,"create:white_sail":37,"create:cogwheel":22,"refurbished_furniture:spruce_cutting_board":1,"minecraft:carrot":11,"create:depot":2,"minecraft:tuff":1,"minecraft:snowball":2,"minecraft:milk_bucket":4,"meadow:cheese_sandwich":1,"meadow:cobbled_limestone":22,"minecraft:spruce_boat":2,"minecraft:glass":11,"minecraft:lava_bucket":7,"minecraft:lantern":8,"refurbished_furniture:light_microwave":1,"refurbished_furniture:white_lamp":1,"minecraft:stone_brick_stairs":156,"meadow:shelf":13,"refurbished_furniture:spruce_chair":4,"farmersdelight:bacon_sandwich":1,"meadow:stove_tiles_bench":6,"minecraft:stone_bricks":185,"meadow:cheese_form":2,"minecraft:scaffolding":231,"minecraft:bow":18,"create:shaft":36,"minecraft:sweet_berries":3,"minecraft:furnace":1,"meadow:stove_tiles_wood":5,"minecraft:beetroot_seeds":3,"minecraft:egg":11,"minecraft:potato":69,"minecraft:oak_chest_boat":2,"minecraft:diorite":9,"minecraft:spruce_door":4,"minecraft:warped_fungus_on_a_stick":24,"regions_unexplored:larch_fence_gate":2,"regions_unexplored:felicia_daisy":1,"minecraft:stone_pickaxe":444,"regions_unexplored:larch_button":35,"refurbished_furniture:light_stove":1,"minecraft:wooden_pickaxe":4,"minecraft:sandstone":16,"meadow:cheese_tart_slice":2,"beautify:hanging_pot":2,"minecraft:diamond_axe":1681,"create:mechanical_saw":11,"minecraft:golden_hoe":8,"minecraft:sand":164,"minecraft:stone_brick_wall":14,"regions_unexplored:larch_slab":106,"regions_unexplored:fireweed":1,"meadow:wooden_cauldron":3,"refurbished_furniture:light_range_hood":1,"minecraft:birch_slab":84,"minecraft:string":2,"minecraft:bread":17,"refurbished_furniture:spruce_table":6,"minecraft:gravel":16,"create:basin":4,"regions_unexplored:cattail":1,"create:vertical_gearbox":12,"regions_unexplored:larch_sapling":5,"minecraft:bone_meal":50,"create:large_cogwheel":15,"refurbished_furniture:door_mat":1,"meadow:chair":4,"minecraft:flint_and_steel":3,"meadow:cooking_cauldron":1,"refurbished_furniture:spruce_kitchen_drawer":2,"minecraft:spruce_planks":53,"refurbished_furniture:light_fridge":2,"minecraft:netherrack":103,"meadow:cooked_buffalo_meat":1,"minecraft:stick":10,"minecraft:torch":377,"minecraft:dirt":21,"create:mechanical_mixer":1,"regions_unexplored:larch_shrub":1,"minecraft:spruce_stairs":75,"meadow:oil_lantern":32,"minecraft:granite":18,"regions_unexplored:hyssop":2,"regions_unexplored:oak_shrub":1,"minecraft:andesite_wall":24,"beautify:lamp_light_bulb":10,"minecraft:iron_hoe":174,"minecraft:stone_brick_slab":34,"minecraft:wooden_axe":119,"regions_unexplored:golden_larch_sapling":5,"minecraft:bookshelf":2,"regions_unexplored:larch_fence":47,"create:wrench":2,"create:gearbox":6,"minecraft:iron_axe":203,"minecraft:rooted_dirt":1,"refurbished_furniture:spruce_kitchen_sink":1,"meadow:can":1,"minecraft:barrel":55,"minecraft:bamboo":34,"regions_unexplored:larch_planks":165,"meadow:stove_tiles_lid":2,"minecraft:trapped_chest":1,"minecraft:cooked_beef":6,"minecraft:cobbled_deepslate":55,"minecraft:powder_snow_bucket":11,"meadow:highland_bed":5,"minecraft:cooked_mutton":3,"minecraft:wheat_seeds":33,"minecraft:water_bucket":72,"minecraft:cobblestone_stairs":9,"regions_unexplored:stripped_larch_log":64,"regions_unexplored:peat_dirt":70,"minecraft:baked_potato":102,"minecraft:spruce_chest_boat":6,"meadow:woodcutter":2,"regions_unexplored:larch_boat":23,"minecraft:oak_slab":1,"minecraft:crafting_table":15,"minecraft:campfire":2,"create:linear_chassis":19,"minecraft:spruce_log":73,"minecraft:book":2,"regions_unexplored:larch_trapdoor":11,"edenring:guide_book":2,"minecraft:diamond_pickaxe":3091,"minecraft:diamond_shovel":85,"create:mechanical_press":1,"create:windmill_bearing":7,"minecraft:chicken":1,"minecraft:iron_pickaxe":1486,"create:water_wheel":7,"minecraft:spruce_trapdoor":54,"regions_unexplored:larch_log":544,"refurbished_furniture:light_electricity_generator":2,"minecraft:spruce_sapling":26,"minecraft:chiseled_stone_bricks":11,"minecraft:cobblestone":89,"refurbished_furniture:workbench":3,"minecraft:bucket":91,"minecraft:glass_pane":1,"minecraft:yellow_bed":2,"minecraft:smooth_stone":10},"minecraft:killed_by":{"minecraft:creeper":1,"minecraft:zombie":7,"minecraft:player":15,"minecraft:spider":1,"minecraft:enderman":2,"minecraft:skeleton":4},"minecraft:crafted":{"refurbished_furniture:spruce_cutting_board":1,"regions_unexplored:larch_fence":45,"minecraft:smooth_stone":20,"minecraft:oak_planks":32,"minecraft:barrel":32,"refurbished_furniture:spruce_kitchen_sink":1,"minecraft:birch_slab":108,"refurbished_furniture:light_microwave":1,"regions_unexplored:larch_planks":716,"minecraft:cobblestone_stairs":8,"refurbished_furniture:knife":1,"minecraft:diamond_shovel":1,"refurbished_furniture:door_mat":1,"create:mechanical_bearing":1,"minecraft:bookshelf":2,"minecraft:cooked_mutton":3,"create:vertical_gearbox":5,"minecraft:quartz_block":1,"minecraft:glass":28,"minecraft:stone_brick_slab":48,"minecraft:bow":1,"minecraft:iron_boots":1,"refurbished_furniture:white_lamp":1,"create:mechanical_press":1,"minecraft:chest":1,"minecraft:chiseled_stone_bricks":9,"create:cogwheel":52,"minecraft:stone_bricks":376,"refurbished_furniture:light_electricity_generator":1,"regions_unexplored:larch_boat":1,"create:depot":1,"create:rose_quartz":8,"minecraft:diamond_axe":2,"minecraft:crafting_table":4,"minecraft:spruce_planks":660,"create:mechanical_saw":7,"minecraft:iron_helmet":1,"minecraft:wooden_pickaxe":1,"minecraft:baked_potato":64,"minecraft:spruce_door":3,"refurbished_furniture:spruce_chair":4,"minecraft:copper_ingot":282,"create:sand_paper":1,"minecraft:birch_planks":56,"minecraft:campfire":2,"create:mechanical_mixer":1,"create:gearbox":10,"minecraft:stone_brick_stairs":124,"minecraft:spruce_trapdoor":48,"minecraft:iron_chestplate":1,"minecraft:charcoal":19,"refurbished_furniture:light_fridge":1,"minecraft:diamond_pickaxe":3,"create:water_wheel":3,"minecraft:shield":1,"create:super_glue":1,"minecraft:stick":136,"minecraft:iron_ingot":62,"minecraft:iron_pickaxe":6,"minecraft:iron_block":2,"minecraft:gold_ingot":49,"create:large_cogwheel":8,"regions_unexplored:larch_fence_gate":1,"beautify:lamp_light_bulb":7,"regions_unexplored:larch_button":33,"create:empty_blaze_burner":1,"minecraft:stone_brick_wall":18,"create:wrench":1,"minecraft:iron_nugget":234,"create:white_sail":24,"minecraft:furnace":1,"refurbished_furniture:light_stove":1,"minecraft:bone_meal":105,"refurbished_furniture:spruce_kitchen_drawer":2,"minecraft:andesite_wall":42,"meadow:oil_lantern":24,"minecraft:glass_pane":32,"minecraft:lantern":8,"minecraft:spruce_stairs":172,"refurbished_furniture:workbench":1,"minecraft:iron_axe":1,"minecraft:iron_hoe":1,"minecraft:slime_ball":9,"minecraft:stone_pickaxe":4,"minecraft:spruce_boat":1,"minecraft:redstone_block":2,"create:basin":1,"create:electron_tube":8,"create:windmill_bearing":2,"minecraft:wheat":18,"minecraft:cooked_beef":5,"create:andesite_alloy":94,"refurbished_furniture:spruce_table":4,"create:goggles":1,"refurbished_furniture:light_range_hood":1,"regions_unexplored:larch_trapdoor":16,"minecraft:bucket":1,"tacz-fabric:gun_smith_table":1,"minecraft:bread":6,"minecraft:air":0,"refurbished_furniture:wrench":1,"refurbished_furniture:spruce_drawer":2,"minecraft:oak_boat":1,"minecraft:oak_chest_boat":1,"create:whisk":1,"minecraft:white_dye":3,"create:linear_chassis":9,"minecraft:wooden_axe":2,"minecraft:iron_shovel":1,"minecraft:iron_leggings":1,"minecraft:stonecutter":1,"create:shaft":120,"regions_unexplored:larch_slab":270,"minecraft:torch":256},"minecraft:picked_up":{"minecraft:wheat":4,"regions_unexplored:larch_planks":87,"minecraft:lead":1,"minecraft:golden_shovel":1,"minecraft:stone_brick_stairs":48,"minecraft:string":6,"minecraft:raw_copper":626,"minecraft:spruce_chest_boat":6,"create:water_wheel":4,"minecraft:gold_nugget":4,"regions_unexplored:bamboo_sapling":2,"minecraft:cobbled_deepslate":233,"farmersdelight:cabbage":2,"minecraft:spruce_planks":3,"regions_unexplored:larch_log":380,"minecraft:calcite":2,"minecraft:iron_pickaxe":2,"farmersdelight:cabbage_seeds":12,"minecraft:stick":57,"meadow:cheese_form":1,"meadow:highland_wool":1,"minecraft:torch":137,"minecraft:spruce_stairs":2,"create:andesite_casing":32,"tacz-fabric:attachment":6,"minecraft:porkchop":20,"minecraft:golden_axe":1,"beautify:lamp_light_bulb":3,"minecraft:diorite":61,"meadow:shelf":7,"regions_unexplored:larch_button":3,"meadow:cheese_sandwich":2,"create:large_cogwheel":4,"minecraft:andesite_wall":1,"meadow:cheese_tart_slice":3,"farmersdelight:fried_egg":2,"minecraft:rotten_flesh":33,"meadow:highland_bed":4,"create:track":6,"supplementaries:ash":9,"minecraft:obsidian":37,"minecraft:snowball":71,"minecraft:cobblestone":520,"regions_unexplored:golden_larch_sapling":7,"minecraft:birch_log":1,"minecraft:cooked_beef":1,"minecraft:warped_fungus_on_a_stick":5,"minecraft:birch_slab":12,"minecraft:andesite":189,"minecraft:potato":162,"minecraft:flint":4,"minecraft:tuff":49,"create:raw_zinc":167,"supplementaries:flax_seeds":1,"refurbished_furniture:spruce_drawer":2,"minecraft:lapis_lazuli":53,"minecraft:dirt":59,"meadow:stove_tiles_lid":1,"meadow:cooked_buffalo_meat":1,"minecraft:bone":17,"minecraft:wheat_seeds":32,"meadow:stove_tiles_wood":4,"minecraft:raw_gold":52,"meadow:table":3,"tacz-fabric:modern_kinetic_gun":3,"create:shaft":9,"regions_unexplored:larch_trapdoor":1,"meadow:cobbled_limestone":28,"regions_unexplored:larch_shrub":1,"minecraft:rabbit":1,"minecraft:bamboo":35,"regions_unexplored:bamboo_log":14,"create:cogwheel":4,"minecraft:sand":275,"regions_unexplored:larch_slab":21,"minecraft:trapped_chest":1,"minecraft:barrel":24,"regions_unexplored:cattail":1,"regions_unexplored:hyssop":2,"minecraft:diamond":17,"minecraft:slime_block":1,"minecraft:spruce_boat":1,"tacz-fabric:ammo":329,"minecraft:granite":33,"minecraft:emerald":2,"minecraft:rooted_dirt":1,"meadow:stove_tiles":2,"minecraft:netherrack":331,"create:white_sail":13,"minecraft:diamond_pickaxe":1,"minecraft:charcoal":2,"regions_unexplored:larch_fence":3,"minecraft:crafting_table":11,"minecraft:chicken":1,"refurbished_furniture:light_fridge":1,"minecraft:stone_brick_wall":1,"meadow:stove_tiles_bench":6,"minecraft:shield":1,"meadow:fire_lily":5,"supplementaries:globe":2,"create:scorchia":1,"minecraft:blackstone":22,"minecraft:beef":14,"refurbished_furniture:light_electricity_generator":1,"create:basin":3,"minecraft:iron_nugget":11,"minecraft:spruce_slab":2,"minecraft:sugar_cane":3,"meadow:alpine_salt":6,"create:linear_chassis":10,"minecraft:spruce_trapdoor":6,"minecraft:egg":12,"minecraft:raw_iron":63,"minecraft:sandstone":405,"minecraft:copper_ingot":98,"minecraft:fire_charge":2,"create:windmill_bearing":5,"meadow:wooden_cauldron":2,"minecraft:carrot":7,"minecraft:redstone":82,"meadow:inky_wool":1,"create:zinc_ingot":64,"create:vertical_gearbox":7,"minecraft:arrow":13,"minecraft:cooked_cod":3,"meadow:oil_lantern":8,"minecraft:golden_hoe":1,"meadow:can":2,"minecraft:hay_block":10,"farmersdelight:bacon_sandwich":1,"create:depot":1,"refurbished_furniture:spruce_table":2,"minecraft:oak_chest_boat":1,"minecraft:mutton":5,"minecraft:white_wool":15,"regions_unexplored:peat_dirt":70,"minecraft:leather":8,"minecraft:filled_map":3,"minecraft:oak_log":9,"minecraft:yellow_bed":1,"minecraft:gunpowder":4,"minecraft:cobblestone_stairs":1,"minecraft:stone_bricks":45,"regions_unexplored:stripped_larch_log":124,"minecraft:kelp":3,"minecraft:heart_of_the_sea":2,"minecraft:iron_ingot":69,"meadow:patched_wool":1,"regions_unexplored:larch_sapling":14,"meadow:eriophorum":1,"create:mechanical_saw":4,"create:mechanical_bearing":2,"minecraft:book":1,"minecraft:scaffolding":405,"minecraft:oak_slab":2,"meadow:woodcutter":3,"minecraft:smooth_basalt":9,"minecraft:pumpkin":12,"minecraft:sweet_berries":3,"minecraft:chiseled_stone_bricks":5,"minecraft:stone_brick_slab":5,"regions_unexplored:oak_shrub":1,"minecraft:gravel":36,"refurbished_furniture:workbench":2,"minecraft:spruce_sapling":60,"minecraft:blast_furnace":1,"minecraft:spruce_log":331,"create:gearbox":1,"minecraft:spruce_door":3,"minecraft:brick_slab":2,"regions_unexplored:fireweed":1,"minecraft:iron_helmet":1,"minecraft:baked_potato":21,"regions_unexplored:larch_boat":23,"minecraft:coal":256,"minecraft:ender_pearl":1},"minecraft:killed":{"minecraft:spider":8,"minecraft:skeleton":13,"minecraft:chicken":1,"minecraft:piglin":1,"minecraft:pig":7,"minecraft:creeper":6,"minecraft:sheep":4,"minecraft:zombie":29,"meadow:wooly_cow":3,"minecraft:cow":4,"minecraft:panda":1,"minecraft:rabbit":2,"minecraft:player":19,"minecraft:enderman":1},"minecraft:mined":{"create:deepslate_zinc_ore":128,"minecraft:spruce_planks":4,"regions_unexplored:golden_larch_leaves":129,"meadow:alpine_salt_ore":6,"regions_unexplored:stripped_larch_log":125,"create:andesite_casing":32,"minecraft:cobblestone_stairs":1,"minecraft:spruce_trapdoor":6,"minecraft:obsidian":37,"regions_unexplored:larch_planks":86,"regions_unexplored:cattail":2,"minecraft:granite":21,"minecraft:stone_brick_wall":1,"minecraft:grass_block":17,"minecraft:cracked_polished_blackstone_bricks":1,"minecraft:soul_soil":5,"minecraft:chiseled_stone_bricks":5,"minecraft:polished_blackstone_bricks":13,"minecraft:magma_block":2,"minecraft:fire":6,"minecraft:iron_ore":24,"minecraft:barrel":24,"minecraft:cobbled_deepslate":3,"meadow:can":2,"regions_unexplored:larch_button":4,"minecraft:pumpkin":12,"supplementaries:globe":3,"minecraft:deepslate_lapis_ore":7,"meadow:highland_bed":4,"supplementaries:stick":3,"regions_unexplored:larch_log":338,"minecraft:spruce_slab":2,"meadow:delphinium":2,"minecraft:tripwire":2,"minecraft:deepslate_redstone_ore":18,"create:cogwheel":4,"meadow:pine_window":1,"minecraft:blackstone":117,"minecraft:soul_fire":1,"minecraft:powder_snow":5,"minecraft:torch":72,"regions_unexplored:cobalt_webbing":3,"minecraft:blast_furnace":1,"regions_unexplored:peat_grass_block":58,"minecraft:calcite":2,"minecraft:nether_quartz_ore":1,"farmersdelight:cabbages":7,"meadow:stove_tiles_bench":6,"minecraft:cobblestone":45,"refurbished_furniture:light_freezer":1,"regions_unexplored:bamboo_log":30,"minecraft:wall_torch":11,"minecraft:deepslate_copper_ore":12,"create:basin":3,"regions_unexplored:hyssop":2,"meadow:stove_tiles_lid":2,"refurbished_furniture:spruce_table":2,"minecraft:wheat":4,"refurbished_furniture:light_electricity_generator":1,"meadow:limestone":28,"meadow:stove_tiles":5,"regions_unexplored:larch_fence":2,"minecraft:stone_brick_stairs":51,"refurbished_furniture:spruce_drawer":2,"minecraft:grass":111,"meadow:table":4,"regions_unexplored:oak_shrub":1,"minecraft:oak_log":8,"regions_unexplored:peat_dirt":8,"minecraft:sand":247,"minecraft:dirt":24,"regions_unexplored:clover":1,"minecraft:smooth_basalt":9,"regions_unexplored:cobalt_nylium":3,"minecraft:nether_gold_ore":6,"minecraft:netherrack":2101,"create:linear_chassis":10,"minecraft:deepslate":249,"regions_unexplored:fireweed":1,"create:zinc_ore":39,"minecraft:tuff":54,"meadow:small_fir":2,"minecraft:deepslate_diamond_ore":17,"regions_unexplored:pink_lupine":1,"farmersdelight:wild_carrots":2,"create:large_cogwheel":4,"create:depot":1,"meadow:oil_lantern":8,"minecraft:birch_slab":9,"minecraft:spruce_leaves":593,"regions_unexplored:raw_redstone_block":48,"minecraft:sandstone":427,"minecraft:rooted_dirt":1,"minecraft:large_fern":4,"minecraft:hay_block":10,"create:shaft":9,"minecraft:spruce_sapling":2,"create:scorchia":51,"regions_unexplored:larch_slab":19,"create:white_sail":13,"meadow:fire_lily":3,"minecraft:andesite":186,"meadow:eriophorum":2,"create:windmill_bearing":3,"regions_unexplored:larch_leaves":143,"minecraft:potatoes":43,"minecraft:deepslate_iron_ore":39,"minecraft:packed_ice":6,"meadow:woodcutter":2,"regions_unexplored:medium_grass":47,"minecraft:bamboo":16,"minecraft:stone":424,"meadow:wooden_cauldron":2,"supplementaries:book_pile_horizontal":1,"minecraft:oak_slab":1,"meadow:cheese_form":1,"minecraft:scaffolding":153,"minecraft:glass_pane":1,"minecraft:soul_sand":26,"minecraft:stone_brick_slab":5,"regions_unexplored:larch_trapdoor":1,"create:track":1,"minecraft:spruce_door":3,"minecraft:crafting_table":10,"meadow:alpine_coal_ore":25,"minecraft:campfire":1,"create:water_wheel":4,"minecraft:andesite_wall":1,"minecraft:copper_ore":169,"minecraft:tall_grass":30,"minecraft:deepslate_coal_ore":17,"meadow:shelf":7,"minecraft:deepslate_gold_ore":52,"regions_unexplored:daisy":1,"create:mechanical_saw":4,"minecraft:diorite":64,"refurbished_furniture:workbench":2,"minecraft:spruce_stairs":3,"supplementaries:urn":12,"regions_unexplored:redstone_bud":1,"create:gearbox":8,"minecraft:ice":1,"minecraft:spruce_log":335,"minecraft:yellow_bed":1,"regions_unexplored:sandy_grass":3,"meadow:stove_tiles_wood":4,"create:mechanical_bearing":2,"minecraft:coal_ore":278,"meadow:enzian":1,"minecraft:gravel":40,"beautify:lamp_light_bulb":1,"minecraft:stone_bricks":45,"minecraft:fern":5,"regions_unexplored:larch_shrub":1},"minecraft:dropped":{"meadow:stove_tiles_bench":2,"minecraft:porkchop":6,"regions_unexplored:larch_planks":3,"minecraft:crafting_table":1,"tacz-fabric:ammo":60,"meadow:woodcutter":1,"minecraft:warped_fungus_on_a_stick":40,"minecraft:flint":2,"minecraft:dirt":14,"regions_unexplored:larch_button":1,"minecraft:cooked_cod":3,"minecraft:snowball":69,"regions_unexplored:golden_larch_sapling":1,"minecraft:sand":2,"meadow:highland_wool":1,"meadow:eriophorum":1,"minecraft:iron_pickaxe":2,"minecraft:white_wool":1,"minecraft:gravel":30,"minecraft:blackstone":18,"minecraft:sugar_cane":1,"minecraft:wheat":1,"minecraft:rotten_flesh":8,"regions_unexplored:larch_sapling":5,"minecraft:golden_shovel":1,"supplementaries:flax_seeds":1,"supplementaries:ash":9,"minecraft:brick_stairs":11,"regions_unexplored:larch_boat":1,"farmersdelight:rope":6,"minecraft:netherrack":309,"minecraft:iron_ingot":32,"minecraft:oak_slab":1,"minecraft:wheat_seeds":8,"minecraft:golden_axe":1,"minecraft:cobblestone":115,"minecraft:copper_ingot":296,"minecraft:coal":32,"minecraft:stick":20,"minecraft:wooden_axe":1,"tacz-fabric:attachment":1,"minecraft:potion":1,"minecraft:golden_hoe":1,"minecraft:heart_of_the_sea":2,"minecraft:string":1,"minecraft:spruce_sapling":22,"minecraft:smooth_basalt":9,"minecraft:kelp":3,"regions_unexplored:larch_log":43,"regions_unexplored:bamboo_log":14,"minecraft:raw_copper":67,"regions_unexplored:larch_slab":39,"minecraft:shield":1,"minecraft:filled_map":4,"meadow:fire_lily":2,"farmersdelight:fried_egg":2,"create:zinc_ingot":320,"minecraft:spruce_planks":28,"minecraft:diamond_pickaxe":1,"minecraft:andesite":34,"minecraft:sandstone":10,"minecraft:stone_pickaxe":1,"minecraft:wooden_pickaxe":1,"minecraft:calcite":2,"minecraft:brick_slab":2,"meadow:cheese_tart_slice":1},"minecraft:broken":{"minecraft:iron_shovel":1,"minecraft:stone_pickaxe":3,"minecraft:diamond_pickaxe":2,"minecraft:wooden_axe":1,"minecraft:iron_axe":1,"minecraft:iron_pickaxe":6,"minecraft:iron_helmet":1,"create:sand_paper":1}},"DataVersion":3465}